{
  "message": "マリオ",
  "ground": [
    {
        "攻撃名": "弱1",
        "発生": "2",
        "隙": "16",
        "ガードF": "3"
    },
    {
        "攻撃名": "弱2",
        "発生": "2",
        "隙": "18",
        "ガードF": "3"
    },
    {
        "攻撃名": "弱3",
        "発生": "3",
        "隙": "29",
        "ガードF": "5"
    },
    {
        "攻撃名": "DA",
        "発生": "6",
        "隙": "28",
        "ガードF": "14"
    },
    {
        "攻撃名": "横強",
        "発生": "5",
        "隙": "18",
        "ガードF": "7"
    },
    {
        "攻撃名": "上強",
        "発生": "5",
        "隙": "18",
        "ガードF": "6"
    },
    {
        "攻撃名": "下強",
        "発生": "5",
        "隙": "20",
        "ガードF": "7"
    },
    {
        "攻撃名": "横スマ",
        "発生": "15",
        "隙": "30",
        "ガードF": "12"
    },
    {
        "攻撃名": "上スマ",
        "発生": "9",
        "隙": "27",
        "ガードF": "10"
    },
    {
        "攻撃名": "下スマ",
        "発生": "5",
        "隙": "29",
        "ガードF": "7"
    }
  ],
  "air": [
    {
        "攻撃名": "空N",
        "発生": "3",
        "隙": "6",
        "ガードF": "4"
    },
    {
        "攻撃名": "空前",
        "発生": "16",
        "隙": "17",
        "ガードF": "6"
    },
    {
        "攻撃名": "空後",
        "発生": "6",
        "隙": "6",
        "ガードF": "4"
    },
    {
        "攻撃名": "空上",
        "発生": "4",
        "隙": "6",
        "ガードF": "3"
    },
    {
        "攻撃名": "空下",
        "発生": "5",
        "隙": "15",
        "ガードF": "3"
    }
  ],
  "b": [
    {
        "攻撃名": "NB",
        "発生": "17",
        "隙": "29",
        "ガードF": "3"
    },
    {
        "攻撃名": "横B",
        "発生": "7",
        "隙": "21",
        "ガードF": "7"
    },
    {
        "攻撃名": "上B",
        "発生": "3",
        "隙": "",
        "ガードF": "6"
    },
    {
        "攻撃名": "下B",
        "発生": "21",
        "隙": "6",
        "ガードF": ""
    }
  ],
  "grab": [
    {
        "攻撃名": "その場",
        "発生": "6",
        "隙": "34",
        "ガードF": ""
    },
    {
        "攻撃名": "ダッシュ",
        "発生": "9",
        "隙": "42",
        "ガードF": ""
    },
    {
        "攻撃名": "振り向き",
        "発生": "10",
        "隙": "36",
        "ガードF": ""
    }
  ]
}